MANIFEST.in
README.rst
setup.cfg
setup.py
arraycontext/__init__.py
arraycontext/context.py
arraycontext/fake_numpy.py
arraycontext/loopy.py
arraycontext/metadata.py
arraycontext/pytest.py
arraycontext/version.py
arraycontext.egg-info/PKG-INFO
arraycontext.egg-info/SOURCES.txt
arraycontext.egg-info/dependency_links.txt
arraycontext.egg-info/requires.txt
arraycontext.egg-info/top_level.txt
arraycontext/container/__init__.py
arraycontext/container/arithmetic.py
arraycontext/container/dataclass.py
arraycontext/container/traversal.py
arraycontext/impl/__init__.py
arraycontext/impl/pyopencl.py
doc/Makefile
doc/array_context.rst
doc/conf.py
doc/container.rst
doc/index.rst
doc/make.bat
doc/misc.rst
doc/other.rst
examples/stub.py
test/test_arraycontext.py